vndb_thigh_highs/__init__.py
vndb_thigh_highs/cache.py
vndb_thigh_highs/command.py
vndb_thigh_highs/config.py
vndb_thigh_highs/dbstats_command.py
vndb_thigh_highs/error.py
vndb_thigh_highs/get_command.py
vndb_thigh_highs/login_command.py
vndb_thigh_highs/response_parser.py
vndb_thigh_highs/set_command.py
vndb_thigh_highs/socket.py
vndb_thigh_highs/vndb.py
vndb_thigh_highs/dumps/__init__.py
vndb_thigh_highs/dumps/tag.py
vndb_thigh_highs/dumps/trait.py
vndb_thigh_highs/dumps/tree.py
vndb_thigh_highs/dumps/vote.py
vndb_thigh_highs/models/__init__.py
vndb_thigh_highs/models/character.py
vndb_thigh_highs/models/common.py
vndb_thigh_highs/models/dbstats.py
vndb_thigh_highs/models/flag.py
vndb_thigh_highs/models/operators.py
vndb_thigh_highs/models/producer.py
vndb_thigh_highs/models/quote.py
vndb_thigh_highs/models/release.py
vndb_thigh_highs/models/staff.py
vndb_thigh_highs/models/table.py
vndb_thigh_highs/models/types.py
vndb_thigh_highs/models/user.py
vndb_thigh_highs/models/user_label.py
vndb_thigh_highs/models/user_vn.py
vndb_thigh_highs/models/vn.py
vndb_thigh_highs-0.1.8.dist-info/LICENSE.md
vndb_thigh_highs-0.1.8.dist-info/METADATA
vndb_thigh_highs-0.1.8.dist-info/WHEEL
vndb_thigh_highs-0.1.8.dist-info/top_level.txt
vndb_thigh_highs-0.1.8.dist-info/RECORD
