Metadata-Version: 2.1
Name: vndb-thigh-highs
Version: 0.1.8
Summary: VNDB api client implementation and dumps helper
Home-page: https://code.blicky.net/FoieGras/vndb-thigh-highs
Author: foiegras
Author-email: foiegras.hkx0v@simplelogin.com
Classifier: Programming Language :: Python :: 3
Classifier: License :: OSI Approved :: GNU Affero General Public License v3
Classifier: Operating System :: OS Independent
License-File: LICENSE.md
